fog05_sdk/DLogger.py
fog05_sdk/__init__.py
fog05_sdk/yaks_connector.py
fog05_sdk/interfaces/AtomicEntity.py
fog05_sdk/interfaces/AtomicEntityRecord.py
fog05_sdk/interfaces/Constants.py
fog05_sdk/interfaces/Entity.py
fog05_sdk/interfaces/EntityRecord.py
fog05_sdk/interfaces/FDU.py
fog05_sdk/interfaces/InfraFDU.py
fog05_sdk/interfaces/MonitoringPlugin.py
fog05_sdk/interfaces/NetworkPlugin.py
fog05_sdk/interfaces/OSPlugin.py
fog05_sdk/interfaces/Plugin.py
fog05_sdk/interfaces/ResourceOrchestratorPlugin.py
fog05_sdk/interfaces/RuntimePluginFDU.py
fog05_sdk/interfaces/States.py
fog05_sdk/interfaces/__init__.py
fog05_sdk/types/__init__.py
fog05_sdk/types/infra_atomic_entity.py
fog05_sdk/types/infra_entity.py
fog05_sdk/types/infra_fdu.py
fog05_sdk/types/user_atomic_entity.py
fog05_sdk/types/user_entity.py
fog05_sdk/types/user_fdu.py
fog05_sdk-0.2.1.dist-info/LICENSE.md
fog05_sdk-0.2.1.dist-info/METADATA
fog05_sdk-0.2.1.dist-info/WHEEL
fog05_sdk-0.2.1.dist-info/top_level.txt
fog05_sdk-0.2.1.dist-info/RECORD
